sentience/__init__.py
sentience/_extension_loader.py
sentience/action_executor.py
sentience/actions.py
sentience/agent.py
sentience/agent_config.py
sentience/agent_runtime.py
sentience/async_api.py
sentience/base_agent.py
sentience/browser.py
sentience/browser_evaluator.py
sentience/canonicalization.py
sentience/captcha.py
sentience/captcha_strategies.py
sentience/cli.py
sentience/cloud_tracing.py
sentience/constants.py
sentience/conversational_agent.py
sentience/cursor_policy.py
sentience/debugger.py
sentience/element_filter.py
sentience/expect.py
sentience/failure_artifacts.py
sentience/formatting.py
sentience/generator.py
sentience/inspector.py
sentience/llm_interaction_handler.py
sentience/llm_provider.py
sentience/llm_provider_utils.py
sentience/llm_response_builder.py
sentience/models.py
sentience/ordinal.py
sentience/overlay.py
sentience/permissions.py
sentience/protocols.py
sentience/query.py
sentience/read.py
sentience/recorder.py
sentience/runtime_agent.py
sentience/screenshot.py
sentience/sentience_methods.py
sentience/snapshot.py
sentience/snapshot_diff.py
sentience/text_search.py
sentience/trace_event_builder.py
sentience/trace_file_manager.py
sentience/tracer_factory.py
sentience/tracing.py
sentience/verification.py
sentience/vision_executor.py
sentience/visual_agent.py
sentience/wait.py
sentience/asserts/__init__.py
sentience/asserts/expect.py
sentience/asserts/query.py
sentience/backends/__init__.py
sentience/backends/actions.py
sentience/backends/browser_use_adapter.py
sentience/backends/cdp_backend.py
sentience/backends/exceptions.py
sentience/backends/playwright_backend.py
sentience/backends/protocol.py
sentience/backends/sentience_context.py
sentience/backends/snapshot.py
sentience/extension/background.js
sentience/extension/content.js
sentience/extension/injected_api.js
sentience/extension/manifest.json
sentience/extension/release.json
sentience/extension/pkg/sentience_core.d.ts
sentience/extension/pkg/sentience_core.js
sentienceapi-0.99.6.dist-info/licenses/LICENSE
sentienceapi-0.99.6.dist-info/licenses/LICENSE-APACHE
sentienceapi-0.99.6.dist-info/licenses/LICENSE-MIT
sentienceapi-0.99.6.dist-info/METADATA
sentienceapi-0.99.6.dist-info/WHEEL
sentienceapi-0.99.6.dist-info/entry_points.txt
sentienceapi-0.99.6.dist-info/top_level.txt
sentienceapi-0.99.6.dist-info/RECORD
