Metadata-Version: 2.4
Name: sentienceapi
Version: 0.99.6
Summary: Python SDK for Sentience AI Agent Browser Automation
Author: Sentience Team
License: MIT OR Apache-2.0
Project-URL: Homepage, https://github.com/SentienceAPI/sentience-python
Project-URL: Repository, https://github.com/SentienceAPI/sentience-python
Project-URL: Issues, https://github.com/SentienceAPI/sentience-python/issues
Keywords: browser-automation,playwright,ai-agent,web-automation,sentience
Classifier: Development Status :: 4 - Beta
Classifier: Intended Audience :: Developers
Classifier: License :: OSI Approved :: MIT License
Classifier: License :: OSI Approved :: Apache Software License
Classifier: Programming Language :: Python :: 3
Classifier: Programming Language :: Python :: 3.11
Requires-Python: >=3.11
License-File: LICENSE
License-File: LICENSE-APACHE
License-File: LICENSE-MIT
Requires-Dist: playwright>=1.40.0
Requires-Dist: pydantic>=2.0.0
Requires-Dist: jsonschema>=4.0.0
Requires-Dist: requests>=2.31.0
Requires-Dist: httpx>=0.25.0
Requires-Dist: playwright-stealth>=1.0.6
Requires-Dist: markdownify>=0.11.6
Provides-Extra: browser-use
Requires-Dist: browser-use>=0.1.40; extra == "browser-use"
Provides-Extra: pydanticai
Requires-Dist: pydantic-ai; extra == "pydanticai"
Provides-Extra: langchain
Requires-Dist: langchain; extra == "langchain"
Requires-Dist: langgraph; extra == "langchain"
Provides-Extra: vision-local
Requires-Dist: pillow>=10.0.0; extra == "vision-local"
Requires-Dist: torch>=2.2.0; extra == "vision-local"
Requires-Dist: transformers>=4.46.0; extra == "vision-local"
Provides-Extra: mlx-vlm
Requires-Dist: pillow>=10.0.0; extra == "mlx-vlm"
Requires-Dist: mlx-vlm>=0.1.0; extra == "mlx-vlm"
Provides-Extra: dev
Requires-Dist: pytest>=7.0.0; extra == "dev"
Requires-Dist: pytest-asyncio>=0.21.0; extra == "dev"
Dynamic: license-file
